redecanais/__init__.py
redecanais/__main__.py
redecanais/player.py
redecanais/redecanais.py
redecanais/settings.py
redecanais/version.py
redecanais-1.0.6.dist-info/LICENSE.txt
redecanais-1.0.6.dist-info/METADATA
redecanais-1.0.6.dist-info/WHEEL
redecanais-1.0.6.dist-info/top_level.txt
redecanais-1.0.6.dist-info/RECORD
