Metadata-Version: 2.1
Name: redecanais
Version: 1.0.6
Summary: Busque,selecione e assista filmes do site https://www.redecanais.com a partir do prompt de comando.
Home-page: https://github.com/cleitonleonel/redecanais.git
Author: Cleiton Leonel Creton
Author-email: cleiton.leonel@gmail.com
License: MIT
Download-URL: https://github.com/cleitonleonel/redecanais/archive/v_01.tar.gz
Keywords: SOME,MEANINGFULL,KEYWORDS
Platform: UNKNOWN
Classifier: Development Status :: 3 - Alpha
Classifier: Intended Audience :: Developers
Classifier: Topic :: Software Development :: Build Tools
Classifier: License :: OSI Approved :: MIT License
Classifier: Programming Language :: Python :: 3
Classifier: Programming Language :: Python :: 3.4
Classifier: Programming Language :: Python :: 3.5
Classifier: Programming Language :: Python :: 3.6
Classifier: Programming Language :: Python :: 3.8
Requires-Dist: requests
Requires-Dist: beautifulsoup4
Requires-Dist: pychromecast
